{"markdown_day_4.2详情页中获取相关推荐.md":"NATHCgnc","markdown_day_2.10瀑布流实现列表渲染.md":"dADYO4fd","markdown_day_2.11瀑布流触底加载更多.md":"H9Yjswb0","markdown_day_4.3详情页中评论列表.md":"15dimRp8","markdown_day_2.3首页search搜索框实现.md":"_jfsNIvo","markdown_day_2.2使用tabbar实现页面切换.md":"V59mQKdk","markdown_day_2.4使用axios封装网络请求.md":"Zc-z3bpt","markdown_day_4.4如何弹出登录框.md":"fZYgFYvR","markdown_index.md":"A2UTFWs3","markdown_day_2.6点击推荐右侧图片进行切换.md":"2Wctz6m5","markdown_day_2.8瀑布流图片计算宽高比.md":"Ka8de9Xf","markdown_day_2.7获取瀑布流图片数据.md":"asSB4u2Q","markdown_day_2.9瀑布流实现列表渲染.md":"Gj8toZ4i","markdown_day_4.1首页跳转详情页.md":"YziUQcan","markdown_day_3.5搜索功能小bug.md":"edkxLVQk","markdown_day_3.6搜索中历史记录的保存.md":"Do0fXcwF","markdown_day_3.3热门城市的显示和隐藏.md":"FpOrgj2U","markdown_day_1.2使用vite初始化项目.md":"VRFuQSUu","markdown_day_1.5使用rem适配.md":"fsk1la4E","markdown_day_1.6配置路径别名@符号.md":"_9_O1CGR","markdown_day_1.7如何在手机中调试项目.md":"lo10nvPJ","markdown_day_2.5渲染首页分类和推荐.md":"LJvkSWsV","markdown_day_3.1热门旅游城市的渲染.md":"2QTvK_Mw","markdown_day_2.1安装并使用vue-router.md":"SHIr-WxA","markdown_day_3.2历史搜索记录的渲染和删除.md":"LzVT6KCL","markdown_design.md":"LprlLayt","index.md":"5K15CwWq","markdown_day_3.4搜索功能-执行搜索.md":"fICo4ps7","markdown_day_1.3vant组件库的安装步骤.md":"5kR5D3c3","readme.md":"jdTGUqvN","markdown_day_1.1开发环境准备.md":"wLW_zcQg","markdown_day_1.4vant组件库中使用field组件.md":"qMffmRBs","markdown_about.md":"kXRIWPST"}
